pytoon/__init__.py
pytoon/__main__.py
pytoon/__version__.py
pytoon/py.typed
pytoon/cli/__init__.py
pytoon/cli/__main__.py
pytoon/cli/main.py
pytoon/core/__init__.py
pytoon/core/decoder.py
pytoon/core/encoder.py
pytoon/core/spec.py
pytoon/decision/__init__.py
pytoon/decision/engine.py
pytoon/decision/metrics.py
pytoon/decoder/__init__.py
pytoon/decoder/depth_decoder.py
pytoon/decoder/lexer.py
pytoon/decoder/parser.py
pytoon/decoder/parser_utils.py
pytoon/decoder/pathexpander.py
pytoon/decoder/scanner.py
pytoon/decoder/statemachine.py
pytoon/decoder/types.py
pytoon/decoder/validator.py
pytoon/encoder/__init__.py
pytoon/encoder/array.py
pytoon/encoder/keyfolding.py
pytoon/encoder/object.py
pytoon/encoder/quoting.py
pytoon/encoder/tabular.py
pytoon/encoder/value.py
pytoon/references/__init__.py
pytoon/references/decoder.py
pytoon/references/encoder.py
pytoon/references/graph.py
pytoon/sparse/__init__.py
pytoon/sparse/polymorphic.py
pytoon/sparse/sparse.py
pytoon/types/__init__.py
pytoon/types/handlers.py
pytoon/types/protocol.py
pytoon/types/py.typed
pytoon/types/registry.py
pytoon/utils/__init__.py
pytoon/utils/errors.py
pytoon/utils/tokens.py
pytoon/utils/validation.py
toon_codec-1.0.1.dist-info/licenses/LICENSE
toon_codec-1.0.1.dist-info/METADATA
toon_codec-1.0.1.dist-info/WHEEL
toon_codec-1.0.1.dist-info/entry_points.txt
toon_codec-1.0.1.dist-info/top_level.txt
toon_codec-1.0.1.dist-info/RECORD
